resco/__init__.py
resco/cli.py
resco/templates.py
resco/utils.py
resco-10.0.data/scripts/resco
resco-10.0.dist-info/DESCRIPTION.rst
resco-10.0.dist-info/METADATA
resco-10.0.dist-info/RECORD
resco-10.0.dist-info/WHEEL
resco-10.0.dist-info/metadata.json
resco-10.0.dist-info/namespace_packages.txt
resco-10.0.dist-info/top_level.txt
resco-10.0.dist-info/zip-safe
