Metadata-Version: 2.0
Name: resco
Version: 10.0
Summary: UNKNOWN
Home-page: UNKNOWN
Author: UNKNOWN
Author-email: UNKNOWN
License: UNKNOWN
Platform: UNKNOWN
Classifier: Development Status :: 3 - Alpha
Classifier: Programming Language :: Python
Requires-Dist: docopt
Requires-Dist: fabric3
Requires-Dist: jinja2
